dnc/__init__.py
dnc/dnc.py
dnc/faiss_index.py
dnc/flann_index.py
dnc/memory.py
dnc/sam.py
dnc/sdnc.py
dnc/sparse_memory.py
dnc/sparse_temporal_memory.py
dnc/util.py
dnc-1.1.0.dist-info/LICENSE
dnc-1.1.0.dist-info/METADATA
dnc-1.1.0.dist-info/WHEEL
dnc-1.1.0.dist-info/top_level.txt
dnc-1.1.0.dist-info/RECORD
